nonebot_plugin_quote/__init__.py
nonebot_plugin_quote/config.py
nonebot_plugin_quote/make_image.py
nonebot_plugin_quote/pilmoji/LICENSE
nonebot_plugin_quote/pilmoji/README.md
nonebot_plugin_quote/pilmoji/__init__.py
nonebot_plugin_quote/pilmoji/core.py
nonebot_plugin_quote/pilmoji/helpers.py
nonebot_plugin_quote/pilmoji/source.py
nonebot_plugin_quote/task.py
nonebot_plugin_quote-0.4.3.dist-info/METADATA
nonebot_plugin_quote-0.4.3.dist-info/WHEEL
nonebot_plugin_quote-0.4.3.dist-info/RECORD
