Metadata-Version: 2.3
Name: nonebot-plugin-quote
Version: 0.4.3
Summary: 一款适用于QQ群聊天的语录库插件
License: MIT
Author: RongRongJi
Author-email: 316315867@qq.com
Requires-Python: >=3.8,<4.0
Classifier: License :: OSI Approved :: MIT License
Classifier: Programming Language :: Python :: 3
Classifier: Programming Language :: Python :: 3.8
Classifier: Programming Language :: Python :: 3.9
Classifier: Programming Language :: Python :: 3.10
Classifier: Programming Language :: Python :: 3.11
Classifier: Programming Language :: Python :: 3.12
Classifier: Programming Language :: Python :: 3.13
Requires-Dist: emoji (>=2.14,<3.0)
Requires-Dist: httpx (>=0.27.2)
Requires-Dist: jieba (>=0.42.1,<0.43.0)
Requires-Dist: nonebot-adapter-onebot (>=2.2.1,<3.0.0)
Requires-Dist: nonebot2 (>=2.0.0rc3,<3.0.0)
Requires-Dist: paddleocr (>=2.9.1,<3.0.0)
Requires-Dist: paddlepaddle (>=2.6.2,<3.0.0)
Requires-Dist: pillow (>=11.1,<11.2)
Requires-Dist: setuptools (>=75.3.0,<76.0.0)
